{
  "2301-11251": {
    "title": "Light-Weight Pointcloud Representation with Sparse Gaussian Process",
    "authors": [
      "Mahmoud Ali",
      "Lantao Liu"
    ],
    "submission_date": "2023-01-26",
    "semantic_scholar_id": "3aee095e0af263159a9c9edb7c0a901dda4437e8"
  },
  "1806-02487": {
    "title": "A Collaborative Aerial-Ground Robotic System for Fast Exploration",
    "authors": [
      "Luqi Wang",
      "Daqian Cheng",
      "Fei Gao",
      "Fengyu Cai",
      "Jixin Guo",
      "Mengxiang Lin",
      "S. Shen"
    ],
    "submission_date": "2018-06-07",
    "semantic_scholar_id": "2688364d5662b1e43b0f9b6057e034e9be6610d2"
  },
  "1610-08733": {
    "title": "GPflow: A Gaussian Process Library using TensorFlow",
    "authors": [
      "A. G. Matthews",
      "Mark van der Wilk",
      "T. Nickson",
      "K. Fujii",
      "A. Boukouvalas",
      "Pablo León-Villagrá",
      "Zoubin Ghahramani",
      "J. Hensman"
    ],
    "submission_date": "2016-10-27",
    "semantic_scholar_id": "c4be5b937c819d1432c5343d1ea07a5269a0380d"
  },
  "1609-07560": {
    "title": "Informative planning and online learning with sparse Gaussian processes",
    "authors": [
      "Kai-Chieh Ma",
      "Lantao Liu",
      "G. Sukhatme"
    ],
    "submission_date": "2016-09-24",
    "semantic_scholar_id": "c17dd3de3ff3f162532a9d60660d381998ed4d9b"
  },
  "1606-04820": {
    "title": "Understanding Probabilistic Sparse Gaussian Process Approximations",
    "authors": [
      "M. Bauer",
      "Mark van der Wilk",
      "C. Rasmussen"
    ],
    "submission_date": "2016-06-15",
    "semantic_scholar_id": "38ee6783f492a43846e4047becd636c1492abdba"
  },
  "1605-00335": {
    "title": "Gaussian processes autonomous mapping and exploration for range-sensing mobile robots",
    "authors": [
      "Maani Ghaffari Jadidi",
      "Jaime Valls Miro",
      "G. Dissanayake"
    ],
    "submission_date": "2016-05-02",
    "semantic_scholar_id": "e3fe830888342aa2b0af62d361211e6103faa906"
  }
}