{
  "2202-02200": {
    "title": "Learning with Neighbor Consistency for Noisy Labels",
    "authors": [
      "Ahmet Iscen",
      "Jack Valmadre",
      "Anurag Arnab",
      "C. Schmid"
    ],
    "submission_date": "2022-02-04",
    "semantic_scholar_id": "682459c9b15bd7bde724f2c151a28278bcd8823b"
  },
  "2110-01242": {
    "title": "Consistency Regularization Can Improve Robustness to Label Noise",
    "authors": [
      "Erik Englesson",
      "Hossein Azizpour"
    ],
    "submission_date": "2021-10-04",
    "semantic_scholar_id": "9af049a648f1f50a40ccff5c95ee2ea366fbddda"
  },
  "2106-10891": {
    "title": "Open-set Label Noise Can Improve Robustness Against Inherent Label Noise",
    "authors": [
      "Hongxin Wei",
      "Lue Tao",
      "Renchunzi Xie",
      "Bo An"
    ],
    "submission_date": "2021-06-21",
    "semantic_scholar_id": "39ccbe81127e44bf3275b94d8b2311367d5c9548"
  },
  "2105-04522": {
    "title": "Generalized Jensen-Shannon Divergence Loss for Learning with Noisy Labels",
    "authors": [
      "Erik Englesson",
      "Hossein Azizpour"
    ],
    "submission_date": "2021-05-10",
    "semantic_scholar_id": "d82bfa043d1f4904202e083d0df834328f1ddb88"
  },
  "2102-11628": {
    "title": "FINE Samples for Learning with Noisy Labels",
    "authors": [
      "Taehyeon Kim",
      "Jongwoo Ko",
      "Sangwook Cho",
      "J. Choi",
      "Se-Young Yun"
    ],
    "submission_date": "2021-02-23",
    "semantic_scholar_id": "6dad270ed83f5aa0a93ff3cb9e78fd069c78c249"
  },
  "2102-02400": {
    "title": "Provably End-to-end Label-Noise Learning without Anchor Points",
    "authors": [
      "Xuefeng Li",
      "Tongliang Liu",
      "Bo Han",
      "Gang Niu",
      "Masashi Sugiyama"
    ],
    "submission_date": "2021-02-04",
    "semantic_scholar_id": "5b0d1cf668c92f23fa9be2e5efe6d8c8ab9376b3"
  },
  "2011-05704": {
    "title": "EvidentialMix: Learning with Combined Open-set and Closed-set Noisy Labels",
    "authors": [
      "Ragav Sachdeva",
      "F. Cordeiro",
      "Vasileios Belagiannis",
      "I. Reid",
      "G. Carneiro"
    ],
    "submission_date": "2020-11-11",
    "semantic_scholar_id": "3783b00111d77b15dd59d55f203133c17d08c9bd"
  },
  "2009-09496": {
    "title": "Learning Soft Labels via Meta Learning",
    "authors": [
      "Nidhi Vyas",
      "S. Saxena",
      "T. Voice"
    ],
    "submission_date": "2020-09-20",
    "semantic_scholar_id": "f9ea8765ddf8a7b2017ffb73c221dce6b57114fa"
  },
  "2007-00151": {
    "title": "Early-Learning Regularization Prevents Memorization of Noisy Labels",
    "authors": [
      "Sheng Liu",
      "Jonathan Niles-Weed",
      "N. Razavian",
      "C. Fernandez‐Granda"
    ],
    "submission_date": "2020-06-30",
    "semantic_scholar_id": "c9b08639a28ab70a06ba9a09eaae98b2fe3dc6c9"
  },
  "2006-13554": {
    "title": "Normalized Loss Functions for Deep Learning with Noisy Labels",
    "authors": [
      "Xingjun Ma",
      "Hanxun Huang",
      "Yisen Wang",
      "Simone Romano",
      "S. Erfani",
      "J. Bailey"
    ],
    "submission_date": "2020-06-24",
    "semantic_scholar_id": "07cca761749bfe21c2d096ff60f32b574d5c84c4"
  },
  "2002-08709": {
    "title": "Do We Need Zero Training Loss After Achieving Zero Training Error?",
    "authors": [
      "Takashi Ishida",
      "Ikko Yamane",
      "Tomoya Sakai",
      "Gang Niu",
      "Masashi Sugiyama"
    ],
    "submission_date": "2020-02-20",
    "semantic_scholar_id": "994e398a62747ce81fa361ff400fa5016ee064dd"
  },
  "2002-07394": {
    "title": "DivideMix: Learning with Noisy Labels as Semi-supervised Learning",
    "authors": [
      "Junnan Li",
      "R. Socher",
      "S. Hoi"
    ],
    "submission_date": "2020-02-18",
    "semantic_scholar_id": "ce435482acc0e195be8d8f002b2655b4c7b08be6"
  },
  "1908-06112": {
    "title": "Symmetric Cross Entropy for Robust Learning With Noisy Labels",
    "authors": [
      "Yisen Wang",
      "Xingjun Ma",
      "Zaiyi Chen",
      "Yuan Luo",
      "Jinfeng Yi",
      "J. Bailey"
    ],
    "submission_date": "2019-08-16",
    "semantic_scholar_id": "3ba8d3060731d64cd46d27e933cbdfb8b7853f4b"
  },
  "1904-11238": {
    "title": "Unsupervised label noise modeling and loss correction",
    "authors": [
      "Eric Arazo Sanchez",
      "Diego Ortego",
      "Paul Albert",
      "N. O’Connor",
      "Kevin McGuinness"
    ],
    "submission_date": "2019-04-25",
    "semantic_scholar_id": "eeecea3097cf5629eb72a06e5caaf24d774adce7"
  },
  "1805-07836": {
    "title": "Generalized Cross Entropy Loss for Training Deep Neural Networks with Noisy Labels",
    "authors": [
      "Zhilu Zhang",
      "M. Sabuncu"
    ],
    "submission_date": "2018-05-20",
    "semantic_scholar_id": "1e1855ca80e8ac3de0e169871f320416902e9ad1"
  },
  "1804-06872": {
    "title": "Co-teaching: Robust training of deep neural networks with extremely noisy labels",
    "authors": [
      "Bo Han",
      "Quanming Yao",
      "Xingrui Yu",
      "Gang Niu",
      "Miao Xu",
      "Weihua Hu",
      "I. Tsang",
      "Masashi Sugiyama"
    ],
    "submission_date": "2018-04-18",
    "semantic_scholar_id": "e061d23b68e7d4aac5aece4794c044c80e638dca"
  },
  "1803-09050": {
    "title": "Learning to Reweight Examples for Robust Deep Learning",
    "authors": [
      "Mengye Ren",
      "Wenyuan Zeng",
      "Binh Yang",
      "R. Urtasun"
    ],
    "submission_date": "2018-03-24",
    "semantic_scholar_id": "c5420ef59d7508d82e53671b0d623027eb58e6ed"
  },
  "1802-05300": {
    "title": "Using Trusted Data to Train Deep Networks on Labels Corrupted by Severe Noise",
    "authors": [
      "Dan Hendrycks",
      "Mantas Mazeika",
      "Duncan Wilson",
      "Kevin Gimpel"
    ],
    "submission_date": "2018-02-14",
    "semantic_scholar_id": "780d18205252a4d3fc1ab4b4a2db55a370d0105e"
  },
  "1712-05055": {
    "title": "MentorNet: Learning Data-Driven Curriculum for Very Deep Neural Networks on Corrupted Labels",
    "authors": [
      "Lu Jiang",
      "Zhengyuan Zhou",
      "Thomas Leung",
      "Li-Jia Li",
      "Li Fei-Fei"
    ],
    "submission_date": "2017-12-14",
    "semantic_scholar_id": "306a2e8ca31fdcc148618d37074785c290f96375"
  },
  "1710-09412": {
    "title": "mixup: Beyond Empirical Risk Minimization",
    "authors": [
      "Hongyi Zhang",
      "Moustapha Cissé",
      "Yann Dauphin",
      "David Lopez-Paz"
    ],
    "submission_date": "2017-10-25",
    "semantic_scholar_id": "4feef0fd284feb1233399b400eb897f59ec92755"
  },
  "1706-05394": {
    "title": "A Closer Look at Memorization in Deep Networks",
    "authors": [
      "Devansh Arpit",
      "Stanislaw Jastrzebski",
      "Nicolas Ballas",
      "David Krueger",
      "Emmanuel Bengio",
      "Maxinder S. Kanwal",
      "Tegan Maharaj",
      "Asja Fischer",
      "Aaron C. Courville",
      "Yoshua Bengio",
      "Simon Lacoste-Julien"
    ],
    "submission_date": "2017-06-16",
    "semantic_scholar_id": "5ddd38a5df945e4afee68d96ed51fd6ca1f7d4cf"
  },
  "1706-02613": {
    "title": "Decoupling \"when to update\" from \"how to update\"",
    "authors": [
      "Eran Malach",
      "Shai Shalev-Shwartz"
    ],
    "submission_date": "2017-06-01",
    "semantic_scholar_id": "0c0017ae798f5850524941597616f87a77bb6226"
  },
  "1702-05659": {
    "title": "On Loss Functions for Deep Neural Networks in Classification",
    "authors": [
      "Katarzyna Janocha",
      "Wojciech M. Czarnecki"
    ],
    "submission_date": "2017-02-18",
    "semantic_scholar_id": "d589392ab606a3d2861988ebcba95176517939ec"
  },
  "1712-09482": {
    "title": "Robust Loss Functions under Label Noise for Deep Neural Networks",
    "authors": [
      "Aritra Ghosh",
      "Himanshu Kumar",
      "P. Sastry"
    ],
    "submission_date": "2017-02-13",
    "semantic_scholar_id": "33d6aa6c41ce3000161d9b5eea910a5b78e14330"
  },
  "1609-03683": {
    "title": "Making Deep Neural Networks Robust to Label Noise: A Loss Correction Approach",
    "authors": [
      "Giorgio Patrini",
      "A. Rozza",
      "A. Menon",
      "R. Nock",
      "Lizhen Qu"
    ],
    "submission_date": "2016-09-13",
    "semantic_scholar_id": "91d331d2bdd5fc86400c40c497bcb4c741c652be"
  },
  "1512-00567": {
    "title": "Rethinking the Inception Architecture for Computer Vision",
    "authors": [
      "Christian Szegedy",
      "Vincent Vanhoucke",
      "Sergey Ioffe",
      "Jonathon Shlens",
      "Z. Wojna"
    ],
    "submission_date": "2015-12-02",
    "semantic_scholar_id": "23ffaa0fe06eae05817f527a47ac3291077f9e58"
  },
  "1505-07634": {
    "title": "Learning with Symmetric Label Noise: The Importance of Being Unhinged",
    "authors": [
      "Brendan van Rooyen",
      "A. Menon",
      "R. C. Williamson"
    ],
    "submission_date": "2015-05-28",
    "semantic_scholar_id": "dd05ce86cacf50e3aee70d633040241923deb120"
  },
  "1502-01178": {
    "title": "Proper Scoring Rules and Bregman Divergences",
    "authors": [
      "E. Ovcharov"
    ],
    "submission_date": "2015-02-04",
    "semantic_scholar_id": "ac28ffeb7c14b1ad442929a85ceb86da383fcdee"
  },
  "1412-6596": {
    "title": "Training Deep Neural Networks on Noisy Labels with Bootstrapping",
    "authors": [
      "Scott E. Reed",
      "Honglak Lee",
      "Dragomir Anguelov",
      "Christian Szegedy",
      "D. Erhan",
      "Andrew Rabinovich"
    ],
    "submission_date": "2014-12-19",
    "semantic_scholar_id": "77e3c48aa10535276e7f570a3af594ba63de7d65"
  },
  "1109-5231": {
    "title": "Noise Tolerance Under Risk Minimization",
    "authors": [
      "Naresh Manwani",
      "S. M. I. P. S. Sastry"
    ],
    "submission_date": "2011-09-23",
    "semantic_scholar_id": "a035210a6dc001a0c3404f94a5c9ec0e73507cfd"
  }
}