{
  "2212-08681": {
    "title": "Plansformer: Generating Symbolic Plans using Transformers",
    "authors": [
      "Vishal Pallagani",
      "Bharath Muppasani",
      "K. Murugesan",
      "F. Rossi",
      "L. Horesh",
      "Biplav Srivastava",
      "F. Fabiano",
      "A. Loreggia"
    ],
    "submission_date": "2022-12-16",
    "semantic_scholar_id": "ae441f7305dc2cd58c708528b3ecee3501cc5c46"
  },
  "1904-03606": {
    "title": "Extending planning knowledge using ontologies for goal opportunities",
    "authors": [
      "Mohannad Babli",
      "E. Onaindía",
      "Eliseo Marzal"
    ],
    "submission_date": "2019-04-07",
    "semantic_scholar_id": "42435238cf84ef797ceee141823d56fe27d67d57"
  },
  "1708-03310": {
    "title": "Thinking, Fast and Slow: Combining Vector Spaces and Knowledge Graphs",
    "authors": [
      "Sudip Mittal",
      "A. Joshi",
      "Timothy W. Finin"
    ],
    "submission_date": "2017-08-10",
    "semantic_scholar_id": "aeab41199894a0828f4d1cfbdb2089cc1a0449b7"
  },
  "1109-6051": {
    "title": "The Fast Downward Planning System",
    "authors": [
      "M. Helmert"
    ],
    "submission_date": "2006-05-01",
    "semantic_scholar_id": "535b3d2d052c4c6d8a7e72e5e7b575aa39bb8b0f"
  }
}