{
  "2212-03954": {
    "title": "Going Beyond XAI: A Systematic Survey for Explanation-Guided Learning",
    "authors": [
      "Yuyang Gao",
      "Siyi Gu",
      "Junji Jiang",
      "S. Hong",
      "Dazhou Yu",
      "Liang Zhao"
    ],
    "submission_date": "2022-12-07",
    "semantic_scholar_id": "025d4b73c1d0f267ca39fa9649413d88ed3cc5bc"
  },
  "2210-06649": {
    "title": "Neuro-Symbolic Explainable Artificial Intelligence Twin for Zero-Touch IoE in Wireless Network",
    "authors": [
      "M. S. Munir",
      "Ki Tae Kim",
      "Apurba Adhikary",
      "W. Saad",
      "Sachin Shetty",
      "Seong-Bae Park",
      "C. Hong"
    ],
    "submission_date": "2022-10-13",
    "semantic_scholar_id": "ce4687601704180679969e30b0c83166dfc6a32e"
  },
  "2205-05406": {
    "title": "Knowledge-Powered Explainable Artificial Intelligence for Network Automation toward 6G",
    "authors": [
      "Yulei Wu",
      "Guozhi Lin",
      "Jingguo Ge"
    ],
    "submission_date": "2022-05-01",
    "semantic_scholar_id": "08e8f6794fe4a397df65496e0470f9bf3c1d117f"
  },
  "2112-04698": {
    "title": "Applications of Explainable AI for 6G: Technical Aspects, Use Cases, and Research Challenges",
    "authors": [
      "Shen Wang",
      "M. Qureshi",
      "Luis Miralles-Pechuán",
      "Thien Huynh-The",
      "T. Gadekallu",
      "Madhusanka Liyanage"
    ],
    "submission_date": "2021-12-09",
    "semantic_scholar_id": "d51066026accde34060d106b2e93eed0e7f3e7b4"
  },
  "2107-05693": {
    "title": "Quantifying Explainability in NLP and Analyzing Algorithms for Performance-Explainability Tradeoff",
    "authors": [
      "Michael J. Naylor",
      "C. French",
      "Samantha R. Terker",
      "Uday Kamath"
    ],
    "submission_date": "2021-07-12",
    "semantic_scholar_id": "a55c86f0d0d443302c1e14769b29835a849ed9d0"
  },
  "2104-01375": {
    "title": "Evaluating Explainable Artificial Intelligence Methods for Multi-label Deep Learning Classification Tasks in Remote Sensing",
    "authors": [
      "Ioannis Kakogeorgiou",
      "K. Karantzalos"
    ],
    "submission_date": "2021-04-03",
    "semantic_scholar_id": "bf4d6ad36ce33b644c820b4f1757606a4eac15b9"
  },
  "2009-11698": {
    "title": "Principles and Practice of Explainable Machine Learning",
    "authors": [
      "Vaishak Belle",
      "I. Papantonis"
    ],
    "submission_date": "2020-09-18",
    "semantic_scholar_id": "b5b98051b65da6b1b3b579862b0407d48c5bef48"
  },
  "2004-13563": {
    "title": "Towards Ubiquitous AI in 6G with Federated Learning",
    "authors": [
      "Yong Xiao",
      "Guangming Shi",
      "M. Krunz"
    ],
    "submission_date": "2020-04-26",
    "semantic_scholar_id": "1e755206520f6f4b007e328288ac0c8760e1affc"
  },
  "2002-02451": {
    "title": "Federated Orchestration for Network Slicing of Bandwidth and Computational Resource",
    "authors": [
      "Yingyu Li",
      "Anqi Huang",
      "Yong Xiao",
      "Xiaohu Ge",
      "Sumei Sun",
      "H. Chao"
    ],
    "submission_date": "2020-02-06",
    "semantic_scholar_id": "48b42865e66f5d68514996f790d1ac06f8a58263"
  },
  "1905-04519": {
    "title": "Interpret Federated Learning with Shapley Values",
    "authors": [
      "Guan Wang"
    ],
    "submission_date": "2019-05-11",
    "semantic_scholar_id": "34aa8d1271e0ee3526b3ebd78def20d36390e0ef"
  },
  "1807-00028": {
    "title": "Training Well-Generalizing Classifiers for Fairness Metrics and Other Data-Dependent Constraints",
    "authors": [
      "Andrew Cotter",
      "Maya R. Gupta",
      "Heinrich Jiang",
      "N. Srebro",
      "Karthik Sridharan",
      "S. Wang",
      "Blake E. Woodworth",
      "Seungil You"
    ],
    "submission_date": "2018-06-29",
    "semantic_scholar_id": "818902d9f339d849e0dfa55ab5d8d8529c145620"
  },
  "1804-06500": {
    "title": "Two-Player Games for Efficient Non-Convex Constrained Optimization",
    "authors": [
      "Andrew Cotter",
      "Heinrich Jiang",
      "Karthik Sridharan"
    ],
    "submission_date": "2018-04-17",
    "semantic_scholar_id": "afe6b57605af91525dad183171e3a850e599841f"
  },
  "1703-01365": {
    "title": "Axiomatic Attribution for Deep Networks",
    "authors": [
      "Mukund Sundararajan",
      "Ankur Taly",
      "Qiqi Yan"
    ],
    "submission_date": "2017-03-04",
    "semantic_scholar_id": "f302e136c41db5de1d624412f68c9174cf7ae8be"
  }
}