{
  "2307-02996": {
    "title": "A Luminous Precursor in the Extremely Bright GRB 230307A",
    "authors": [
      "S. Dichiara",
      "D. Tsang",
      "E. Troja",
      "D. Neill",
      "J. Norris",
      "Y.-H. Yang"
    ],
    "submission_date": "2023-07-06",
    "semantic_scholar_id": "7ab94fddb0da0b3d3ca815f1479f9953e600fbd8"
  },
  "2303-11083": {
    "title": "A Broken “α–intensity” Relation Caused by the Evolving Photosphere Emission and the Nature of the Extraordinarily Bright GRB 230307A",
    "authors": [
      "Yun Wang",
      "Z. Xia",
      "T. Zheng",
      "Jia Ren",
      "Yizhong Fan"
    ],
    "submission_date": "2023-03-20",
    "semantic_scholar_id": "5bae658b9f1b38b3928abbd8c6ffbb1ac0065332"
  },
  "2302-14037": {
    "title": "GRB 221009A: The BOAT",
    "authors": [
      "E. Burns",
      "D. Svinkin",
      "E. Fenimore",
      "D. A. Kann",
      "J. Feliciano",
      "Agüí Fernández",
      "D. Frederiks",
      "R. Hamburg",
      "S. Lesage",
      "Yu. R. Temiraev",
      "A. Tsvetkova",
      "E. Bissaldi",
      "M. Briggs",
      "S. Dalessi",
      "Rachel Dunwoody",
      "C. Fletcher",
      "A. Goldstein",
      "C. Hui",
      "B. Hristov",
      "D. Kocevski",
      "A. Lysenko",
      "B. Mailyan",
      "Joe Mangan",
      "S. McBreen",
      "J. Racusin",
      "A. Ridnaia",
      "O. Roberts",
      "M. Ulanov",
      "P. Veres",
      "C. Wilson-Hodge",
      "J. Wood"
    ],
    "submission_date": "2023-02-27",
    "semantic_scholar_id": "7493ebc56f38a871ea3d21d300a8c62fd1d960e2"
  },
  "2302-13383": {
    "title": "Properties of the Extremely Energetic GRB 221009A from Konus-WIND and SRG/ART-XC Observations",
    "authors": [
      "D. Frederiks",
      "D. Svinkin",
      "A. Lysenko",
      "S. Molkov",
      "A. Tsvetkova",
      "M. Ulanov",
      "A. Ridnaia",
      "A. Lutovinov",
      "I. Lapshov",
      "A. Tkachenko",
      "V. Levin"
    ],
    "submission_date": "2023-02-26",
    "semantic_scholar_id": "f2ba1d37f72a0c64d513b8e8f3fcc0207324f779"
  },
  "2302-11518": {
    "title": "The Power of the Rings: The GRB 221009A Soft X-Ray Emission from Its Dust-scattering Halo",
    "authors": [
      "A. Tiengo",
      "F. Pintore",
      "B. Vaia",
      "Simone Filippi",
      "Andrea Sacchi",
      "P. Esposito",
      "M. Rigoselli",
      "S. Mereghetti",
      "R. Salvaterra",
      "Barbara Šiljeg",
      "A. Bracco",
      "Ž. Bošnjak",
      "V. Jelić",
      "S. Campana"
    ],
    "submission_date": "2023-02-22",
    "semantic_scholar_id": "736b543e38452950a1ed9ece40686ef9771bd459"
  },
  "2301-09292": {
    "title": "Investigating Time Variability of X-Ray Absorption in Swift GRBs",
    "authors": [
      "V. Valan",
      "J. Larsson",
      "B. Ahlgren"
    ],
    "submission_date": "2023-01-23",
    "semantic_scholar_id": "0f71b4c826ca5789a2a795481e4969ce5669967d"
  },
  "2209-03363": {
    "title": "A nearby long gamma-ray burst from a merger of compact objects",
    "authors": [
      "E. Troja",
      "Chris L. Fryer",
      "B. O’Connor",
      "G. Ryan",
      "S. Dichiara",
      "A. Kumar",
      "N. Ito",
      "R. Gupta",
      "R. Wollaeger",
      "J. Norris",
      "N. Kawai",
      "N. Butler",
      "A. Aryan",
      "K. Misra",
      "R. Hosokawa",
      "K. Murata",
      "M. Niwano",
      "S. Pandey",
      "A. Kutyrev",
      "H. van Eerten",
      "E. Chase",
      "Y.-D. Hu",
      "M. Caballero-García",
      "A. Castro-Tirado"
    ],
    "submission_date": "2022-09-07",
    "semantic_scholar_id": "56a8f655d3ee6663852d1de286bc268d09ff6c0b"
  },
  "2204-12771": {
    "title": "A long-duration gamma-ray burst with a peculiar origin",
    "authors": [
      "J. Yang",
      "Shunke Ai",
      "Binbin Zhang",
      "Bing Zhang",
      "Zibo Liu",
      "X. Wang",
      "Yu-Han Yang",
      "Yi-Han Yin",
      "Ye Li",
      "Hou-Jun Lu"
    ],
    "submission_date": "2022-04-27",
    "semantic_scholar_id": "6a716508a60e7bb5c2b69d61df442ca5d2261951"
  },
  "2204-10864": {
    "title": "A kilonova following a long-duration gamma-ray burst at 350 Mpc",
    "authors": [
      "J. Rastinejad",
      "B. Gompertz",
      "A. Levan",
      "W. Fong",
      "M. Nicholl",
      "G. Lamb",
      "D. Malesani",
      "A. Nugent",
      "S. Oates",
      "N. Tanvir",
      "A. de Ugarte Postigo",
      "C. Kilpatrick",
      "C. Moore",
      "B. Metzger",
      "M. Ravasio",
      "A. Rossi",
      "G. Schroeder",
      "J. Jencson",
      "D. Sand",
      "N. Smith",
      "José Feliciano Agüí Fernández",
      "E. Berger",
      "P. Blanchard",
      "R. Chornock",
      "B. Cobb",
      "M. De Pasquale",
      "J. Fynbo",
      "L. Izzo",
      "D. A. Kann",
      "T. Laskar",
      "E. Marini",
      "K. Paterson",
      "A. R. Escorial",
      "H. Sears",
      "C. Thöne"
    ],
    "submission_date": "2022-04-22",
    "semantic_scholar_id": "10c230551ac684a2533340ca99da08393de72f30"
  },
  "2203-01627": {
    "title": "Updated Gaia-2MASS 3D maps of Galactic interstellar dust",
    "authors": [
      "R. Lallement",
      "J. Vergely",
      "C. Babusiaux",
      "N. Cox"
    ],
    "submission_date": "2022-03-03",
    "semantic_scholar_id": "20ea23f125aaf2b53cb4f1f2a6292d255c28ea37"
  },
  "2201-03152": {
    "title": "Dust distributions in the Magellanic Clouds",
    "authors": [
      "B.-Q. Chen",
      "H.-L. Guo",
      "J. Gao",
      "M. Yang",
      "Y.L. Liu",
      "B. Jiang"
    ],
    "submission_date": "2022-01-10",
    "semantic_scholar_id": "4bdc4235e22e39d235ba8c0baebefe3cefa59c58"
  },
  "2105-05067": {
    "title": "Author Correction: Discovery and confirmation of the shortest gamma-ray burst from a collapsar",
    "authors": [
      "T. Ahumada",
      "L. Singer",
      "S. Anand",
      "M. Coughlin",
      "M. Kasliwal",
      "G. Ryan",
      "I. Andreoni",
      "S. Cenko",
      "C. Fremling",
      "H. Kumar",
      "P. T. Pang",
      "E. Burns",
      "V. Cunningham",
      "S. Dichiara",
      "T. Dietrich",
      "D. Svinkin",
      "M. Almualla",
      "A. Castro-Tirado",
      "K. De",
      "Rachel Dunwoody",
      "P. Gatkine",
      "E. Hammerstein",
      "S. Iyyani",
      "Joe Mangan",
      "D. Perley",
      "S. Purkayastha",
      "E. Bellm",
      "V. Bhalerao",
      "B. Bolin",
      "M. Bulla",
      "C. Cannella",
      "P. Chandra",
      "D. Duev",
      "D. Frederiks",
      "A. Gal-yam",
      "M. Graham",
      "A. Ho",
      "K. Hurley",
      "V. Karambelkar",
      "Erik C.Kool",
      "S. Kulkarni",
      "A. Mahabal",
      "F. Masci",
      "S. McBreen",
      "S. Pandey",
      "S. Reusch",
      "A. Ridnaia",
      "P. Rosnet",
      "B. Rusholme",
      "A. Carracedo",
      "Roger M. Smith",
      "M. Soumagnac",
      "R. Stein",
      "E. Troja",
      "A. Tsvetkova",
      "R. Walters",
      "A. Valeev"
    ],
    "submission_date": "2021-05-11",
    "semantic_scholar_id": "fe45b5ba7edd10b27bfc718b8ee6fdf04bea0948"
  },
  "2105-03829": {
    "title": "The Peculiar Short-duration GRB 200826A and Its Supernova",
    "authors": [
      "A. Rossi",
      "Barry Rothberg",
      "E. Palazzi",
      "D. A. Kann",
      "P. D’Avanzo",
      "L. Amati",
      "S. Klose",
      "A. Perego",
      "E. Pian",
      "C. Guidorzi",
      "A. Pozanenko",
      "S. Savaglio",
      "G. Stratta",
      "G. Agapito",
      "S. Covino",
      "F. Cusano",
      "V. D’Elia",
      "M. Pasquale",
      "M. Valle",
      "O. Kuhn",
      "L. Izzo",
      "E. Loffredo",
      "N. Masetti",
      "A. Melandri",
      "P. Minaev",
      "A. N. Guelbenzu",
      "D. Paris",
      "S. Paiano",
      "C. Plantet",
      "F. Rossi",
      "R. Salvaterra",
      "S. Schulze",
      "C. Veillet",
      "A. Volnova"
    ],
    "submission_date": "2021-05-09",
    "semantic_scholar_id": "43cd293aa2bfe0f71fae45e08e3b22e148c9df18"
  },
  "2103-05735": {
    "title": "The variable absorption in the X-ray spectrum of GRB 190114C",
    "authors": [
      "S. Campana",
      "D. Lazzati",
      "R. Perna",
      "Maria Grazia Bernardini",
      "L. Nava"
    ],
    "submission_date": "2021-03-09",
    "semantic_scholar_id": "e1920785dadede2da0bb39a5762545754ebac963"
  },
  "2012-01771": {
    "title": "Gaia Early Data Release 3: Structure and properties of the Magellanic Clouds",
    "authors": [
      "Gaia Collaboration",
      "A. Brown",
      "A. Vallenari",
      "T. Prusti",
      "J. Bruijne",
      "C. Babusiaux",
      "M. Biermann",
      "O. Creevey",
      "D. Evans",
      "L. Eyer",
      "A. Hutton",
      "F. Jansen",
      "C. Jordi",
      "S. Klioner",
      "U. Lammers",
      "L. Lindegren",
      "X. Luri",
      "F. Mignard",
      "C. Panem",
      "D. Pourbaix",
      "S. Randich",
      "P. Sartoretti",
      "C. Soubiran",
      "N. Walton",
      "Frédéric Arenou",
      "C. Bailer-Jones",
      "U. Bastian",
      "M. Cropper",
      "R. Drimmel",
      "D. Katz",
      "M. Lattanzi",
      "F. V. Leeuwen",
      "J. Bakker",
      "C. Cacciari",
      "J. Castañeda",
      "F. Angeli",
      "C. Ducourant",
      "C. Fabricius",
      "M. Fouesneau",
      "Y. Fr'emat",
      "R. Guerra",
      "A. Guerrier",
      "J. Guiraud",
      "A. Piccolo",
      "E. Masana",
      "R. Messineo",
      "N. Mowlavi",
      "C. Nicolas",
      "K. Nienartowicz",
      "F. Pailler",
      "P. Panuzzo",
      "F. Riclet",
      "W. Roux",
      "G. Seabroke",
      "R. Sordo",
      "P. Tanga",
      "F. Th'evenin",
      "G. Gracia-Abril",
      "J. Portell",
      "D. Teyssier",
      "M. Altmann",
      "R. Andrae",
      "I. Bellas-Velidis",
      "K. Benson",
      "J. Berthier",
      "R. Blomme",
      "E. Brugaletta",
      "P. Burgess",
      "G. Busso",
      "B. Carry",
      "A. Cellino",
      "N. Cheek",
      "G. Clementini",
      "Y. Damerdji",
      "M. Davidson",
      "L. Delchambre",
      "A. Dell’Oro",
      "J. Fern'andez-Hern'andez",
      "L. Galluccio",
      "P. Garc'ia-Lario",
      "M. Garcia-Reinaldos",
      "J. Gonz'alez-N'unez",
      "E. Gosset",
      "R. Haigron",
      "J. Halbwachs",
      "N. Hambly",
      "D. Harrison",
      "D. Hatzidimitriou",
      "U. Heiter",
      "J. Hern'andez",
      "D. Hestroffer",
      "S. Hodgkin",
      "B. Holl",
      "K. Janssen",
      "G. D. Fombelle",
      "S. Jordan",
      "A. Krone-Martins",
      "A. Lanzafame",
      "W. L. offler",
      "A. Lorca",
      "M. Manteiga",
      "O. Marchal",
      "P. Marrese",
      "A. Moitinho",
      "A. Mora",
      "K. Muinonen",
      "P. Osborne",
      "E. Pancino",
      "T. Pauwels",
      "J. Petit",
      "A. Recio-Blanco",
      "P. J. Richards",
      "M. Riello",
      "L. Rimoldini",
      "A. Robin",
      "T. Roegiers",
      "J. Rybizki",
      "L. Sarro",
      "C. Siopis",
      "M. Smith",
      "A. Sozzetti",
      "A. Ulla",
      "E. Utrilla",
      "M. V. Leeuwen",
      "W. V. Reeven",
      "U. Abbas",
      "A. Aramburu",
      "S. Accart",
      "C. Aerts",
      "J. J. Aguado",
      "M. Ajaj",
      "G. Altavilla",
      "M. A. Álvarez",
      "J. '. Cid-Fuentes",
      "J. Alves",
      "R. I. Anderson",
      "E. A. Varela",
      "T. Antoja",
      "M. Audard",
      "D. Baines",
      "S. Baker",
      "L. Balaguer-N'unez",
      "E. Balbinot",
      "Z. Balog",
      "C. Barache",
      "D. Barbato",
      "M. Barros",
      "M. Barstow",
      "S. Bartolom'e",
      "J.-L. Bassilana",
      "N. Bauchet",
      "A. Baudesson-Stella",
      "U. Becciani",
      "M. Bellazzini",
      "M. Bernet",
      "S. Bertone",
      "L. Bianchi",
      "Sergi Blanco-Cuaresma",
      "T. Boch",
      "A. Bombrun",
      "D. Bossini",
      "S. Bouquillon",
      "A. Bragaglia",
      "L. Bramante",
      "E. Breedt",
      "A. Bressan",
      "N. Brouillet",
      "B. Bucciarelli",
      "A. Burlacu",
      "D. Busonero",
      "A. Butkevich",
      "R. Buzzi",
      "E. Caffau",
      "R. Cancelliere",
      "H. C'anovas",
      "T. Cantat-Gaudin",
      "R. Carballo",
      "T. Carlucci",
      "M. I. Carnerero",
      "J. Carrasco",
      "L. Casamiquela",
      "M. Castellani",
      "A. Castro-Ginard",
      "P. Sampol",
      "L. Chaoul",
      "P. Charlot",
      "L. Chemin",
      "A. Chiavassa",
      "M. Cioni",
      "G. Comoretto",
      "W. J. Cooper",
      "T. Cornez",
      "S. Cowell",
      "F. Crifo",
      "M. Crosta",
      "C. Crowley",
      "C. Dafonte",
      "A. Dapergolas",
      "M. David",
      "P. David",
      "P. Laverny",
      "F. Luise",
      "R. March",
      "J. Ridder",
      "R. D. Souza",
      "P. D. Teodoro",
      "A. Torres",
      "E. F. D. Peloso",
      "E. D. Pozo",
      "M. Delbo’",
      "A. Delgado",
      "H. E. Delgado",
      "J. Delisle",
      "P. Matteo",
      "S. Diakite",
      "C. Diener",
      "E. Distefano",
      "C. Dolding",
      "D. Eappachen",
      "B. Edvardsson",
      "H. Enke",
      "P. Esquej",
      "C. Fabre",
      "M. Fabrizio",
      "S. Faigler",
      "G. Fedorets",
      "P. Fernique",
      "A. Fienga",
      "F. Figueras",
      "C. Fouron",
      "F. Fragkoudi",
      "E. Fraile",
      "F. Franke",
      "M. Gai",
      "D. Garabato",
      "A. García-Gutiérrez",
      "M. Garc'ia-Torres",
      "A. Garofalo",
      "P. Gavras",
      "E. Gerlach",
      "R. Geyer",
      "P. Giacobbe",
      "G. Gilmore",
      "S. Girona",
      "G. Giuffrida",
      "R. Gomel",
      "A. Gómez",
      "I. González-Santamaría",
      "J. J. Gonz'alez-Vidal",
      "M. Granvik",
      "R. Guti'errez-S'anchez",
      "L. Guy",
      "M. Hauser",
      "M. Haywood",
      "A. Helmi",
      "S. Hidalgo",
      "T. Hilger",
      "N. Hładczuk",
      "D. Hobbs",
      "G. Holland",
      "H. Huckle",
      "G. Jasniewicz",
      "P. Jonker",
      "J. Campillo",
      "F. Julbé",
      "L. Karbevska",
      "P. Kervella",
      "S. Khanna",
      "A. Kochoska",
      "M. Kontizas",
      "G. Kordopatis",
      "A. Korn",
      "Z. Kostrzewa-Rutkowska",
      "K. Kruszy'nska",
      "S. Lambert",
      "A. Lanza",
      "Y. Lasne",
      "J. L. Campion",
      "Y. L. Fustec",
      "Y. Lebreton",
      "T. Lebzelter",
      "S. Leccia",
      "N. Leclerc",
      "I. Lecoeur-Taibi",
      "S. Liao",
      "E. Licata",
      "H. Lindstrøm",
      "T. Lister",
      "E. Livanou",
      "A. Lobel",
      "P. Pardo",
      "S. Managau",
      "R. Mann",
      "J. Marchant",
      "M. Marconi",
      "M.M.S. Marcos Santos",
      "S. Marinoni",
      "F. Marocco",
      "D. Marshall",
      "L. M. Polo",
      "J. Mart'in-Fleitas",
      "A. Masip",
      "D. Massari",
      "A. Mastrobuono-Battisti",
      "T. Mazeh",
      "P. McMillan",
      "S. Messina",
      "D. Michalik",
      "N. Millar",
      "A. Mints",
      "D. Molina",
      "R. Molinaro",
      "L. Moln'ar",
      "P. Montegriffo",
      "R. Mor",
      "R. Morbidelli",
      "T. Morel",
      "D. Morris",
      "A. Mulone",
      "D. Munoz",
      "T. Muraveva",
      "C. P. Murphy",
      "I. Musella",
      "L. Noval",
      "C. Ord'enovic",
      "G. Orrú",
      "J. Osinde",
      "C. Pagani",
      "I. Pagano",
      "L. Palaversa",
      "P. Palicio",
      "A. Panahi",
      "M. Pawlak",
      "X. P. Esteller",
      "A. a",
      "A. Piersimoni",
      "F. Pineau",
      "E. Plachy",
      "G. Plum",
      "E. Poggio",
      "E. Poretti",
      "E. Poujoulet",
      "A. Prvsa",
      "L. Pulone",
      "E. Racero",
      "S. Ragaini",
      "M. Rainer",
      "C. Raiteri",
      "N. Rambaux",
      "P. Ramos",
      "M. Ramos-Lerate",
      "P. Fiorentin",
      "S. Regibo",
      "C. Reyl'e",
      "V. Ripepi",
      "A. Riva",
      "G. Rixon",
      "N. Robichon",
      "C. Robin",
      "M. Roelens",
      "L. Rohrbasser",
      "M. Romero-G'omez",
      "N. Rowell",
      "F. Royer",
      "K. Rybicki",
      "G. Sadowski",
      "A. S. Sell'es",
      "J. Sahlmann",
      "J. Salgado",
      "E. Salguero",
      "N. Samaras",
      "V. S. Gimenez",
      "N. Sanna",
      "R. Santoveña",
      "M. Sarasso",
      "M. Schultheis",
      "E. Sciacca",
      "M. Ségol",
      "J. Segovia",
      "D. S'egransan",
      "D. Semeux",
      "S. Shahaf",
      "H. Siddiqui",
      "A. Siebert",
      "L. Siltala",
      "É. Slezak",
      "R. Smart",
      "E. Solano",
      "F. Solitro",
      "D. Souami",
      "J. Souchay",
      "A. Spagna",
      "F. Spoto",
      "I. Steele",
      "H. S. uller",
      "C. Stephenson",
      "M. uveges",
      "L. Szabados",
      "E. Szegedi-Elek",
      "F. Taris",
      "G. Tauran",
      "M. B. Taylor",
      "R. Teixeira",
      "W. Thuillot",
      "N. Tonello",
      "F. Torra",
      "J. Torra",
      "C. Turon",
      "N. Unger",
      "M. Vaillant",
      "E. W. Dillen",
      "O. Vanel",
      "A. Vecchiato",
      "Y. Viala",
      "D. Vicente",
      "S. Voutsinas",
      "M. Weiler",
      "T. Wevers",
      "L. Wyrzykowski",
      "A. Yoldas",
      "P. Yvard",
      "H. Zhao",
      "J. Zorec",
      "S. Zucker",
      "C. Zurbach",
      "T. Zwitter"
    ],
    "submission_date": "2020-12-03",
    "semantic_scholar_id": "14f484c2db512a450ec7465085237e374fee737a"
  },
  "1807-06177": {
    "title": "Identifying quasars with astrometric and mid-infrared methods from APOP and ALLWISE",
    "authors": [
      "Sufen Guo",
      "Z. Qi",
      "S. Liao",
      "Z. Cao",
      "M. Lattanzi",
      "B. Bucciarelli",
      "Zheng-hong Tang",
      "Q. Yan"
    ],
    "submission_date": "2018-07-17",
    "semantic_scholar_id": "182a6514c276652a9b6d2050b99770ab15d41b2b"
  },
  "1804-08821": {
    "title": "A compilation of known QSOs for the Gaia mission",
    "authors": [
      "S. Liao",
      "Z. Qi",
      "Sufen Guo",
      "Z. Cao"
    ],
    "submission_date": "2018-04-24",
    "semantic_scholar_id": "082456b3297330b64cc4a48fa9e1b4b9d31f2bb3"
  },
  "1710-05446": {
    "title": "An Ordinary Short Gamma-Ray Burst with Extraordinary Implications: Fermi-GBM Detection of GRB 170817A",
    "authors": [
      "A. Goldstein",
      "P. Veres",
      "E. Burns",
      "M. Briggs",
      "R. Hamburg",
      "D. Kocevski",
      "C. Wilson-Hodge",
      "R. Preece",
      "S. Poolakkil",
      "O. Roberts",
      "C. Hui",
      "V. Connaughton",
      "J. Racusin",
      "A. Kienlin",
      "T. D. Canton",
      "N. Christensen",
      "N. Christensen",
      "T. Littenberg",
      "K. Siellez",
      "L. Blackburn",
      "J. Broida",
      "E. Bissaldi",
      "E. Bissaldi",
      "W. Cleveland",
      "M. Gibby",
      "M. Giles",
      "R. Kippen",
      "S. McBreen",
      "J. Mcenery",
      "C. Meegan",
      "W. Paciesas",
      "M. Stanbro"
    ],
    "submission_date": "2017-10-16",
    "semantic_scholar_id": "454271d48458fa08ef183bdb9786cb6eb1fec2fe"
  },
  "1710-05449": {
    "title": "INTEGRAL Detection of the First Prompt Gamma-Ray Signal Coincident with the Gravitational-wave Event GW170817",
    "authors": [
      "V. Savchenko",
      "C. Ferrigno",
      "E. Kuulkers",
      "A. Bazzano",
      "E. Bozzo",
      "S. Brandt",
      "J. Chenevez",
      "T. Courvoisier",
      "R. Diehl",
      "A. Domingo",
      "L. Hanlon",
      "E. Jourdain",
      "A. Kienlin",
      "P. Laurent",
      "F. Lebrun",
      "A. Lutovinov",
      "A. Martin-Carrillo",
      "S. Mereghetti",
      "L. Natalucci",
      "J. Rodi",
      "J. Roques",
      "R. Sunyaev",
      "P. Ubertini"
    ],
    "submission_date": "2017-10-16",
    "semantic_scholar_id": "dc827a3cf620781601e89de62ad6d01c22bc69c4"
  },
  "1708-08835": {
    "title": "Behind the dust curtain: the spectacular case of GRB 160623A",
    "authors": [
      "F. Pintore",
      "A. Tiengo",
      "A. Tiengo",
      "S. Mereghetti",
      "G. Vianello",
      "R. Salvaterra",
      "P. Esposito",
      "E. Costantini",
      "A. Giuliani",
      "Ž. Bošnjak"
    ],
    "submission_date": "2017-08-29",
    "semantic_scholar_id": "e5b41264ee1b9849a5e770c5da67e63e7940f57c"
  },
  "1704-01633": {
    "title": "INTEGRAL IBIS, SPI, and JEM-X observations of LVT151012",
    "authors": [
      "V. Savchenko",
      "A. Bazzano",
      "E. Bozzo",
      "S. Brandt",
      "J. Chenevez",
      "T. Courvoisier",
      "R. Diehl",
      "C. Ferrigno",
      "L. Hanlon",
      "A. Kienlin",
      "E. Kuulkers",
      "P. Laurent",
      "F. Lebrun",
      "A. Lutovinov",
      "A. Lutovinov",
      "A. Martin-Carrillo",
      "S. Mereghetti",
      "L. Natalucci",
      "J. Roques",
      "T. Siegert",
      "R. Sunyaev",
      "P. Ubertini"
    ],
    "submission_date": "2017-04-05",
    "semantic_scholar_id": "8a1b68c7552b1d61035877d597da434e96f0822d"
  },
  "1610-06175": {
    "title": "HI4PI: a full-sky H i survey based on EBHIS and GASS",
    "authors": [
      "N. B. Bekhti",
      "L. Flöer",
      "R. Keller",
      "J. Kerp",
      "D. Lenz",
      "B. Winkel",
      "J. Bailin",
      "M. Calabretta",
      "L. Dedes",
      "H. Ford",
      "B. Gibson",
      "U. Haud",
      "S. Janowiecki",
      "P. Kalberla",
      "F. J. Lockman",
      "N. McClure-Griffiths",
      "T. Murphy",
      "H. Nakanishi",
      "D. Pisano",
      "L. Staveley-Smith"
    ],
    "submission_date": "2016-10-01",
    "semantic_scholar_id": "69c0a96958a81d0b8942947606f6240763e06c92"
  },
  "1503-07761": {
    "title": "A possible macronova in the late afterglow of the long–short burst GRB 060614",
    "authors": [
      "Bin Yang",
      "Z. Jin",
      "Xiang Li",
      "S. Covino",
      "Xianzhong Zheng",
      "K. Hotokezaka",
      "Yizhong Fan",
      "T. Piran",
      "D. Wei"
    ],
    "submission_date": "2015-03-26",
    "semantic_scholar_id": "2a3538a73cf309f0ed60af405e2501e7caaa21f7"
  },
  "1105-1312": {
    "title": "GRB 090426: Discovery of a jet break in a short burst afterglow",
    "authors": [
      "A. N. Guelbenzu",
      "S. Klose",
      "A. Rossi",
      "D. A. Kann",
      "T. Krühler",
      "J. Greiner",
      "A. Rau",
      "F. Olivares",
      "P. Afonso",
      "R. Filgas",
      "A. Yoldas",
      "S. McBreen",
      "M. Nardini",
      "P. Schady",
      "S. Schmidl",
      "A. Updike",
      "A. Updike",
      "A. Updike",
      "A. Yoldas"
    ],
    "submission_date": "2011-05-06",
    "semantic_scholar_id": "9ee245ee603af777744bc6f711bcc1c7e904b09d"
  },
  "0911-0046": {
    "title": "GRB 090426: the farthest short gamma-ray burst?",
    "authors": [
      "L. A. Antonelli",
      "P. D’Avanzo",
      "P. D’Avanzo",
      "R. Perna",
      "L. Amati",
      "S. Covino",
      "S. Cutini",
      "V. D’Elia",
      "S. Gallozzi",
      "A. Grazian",
      "E. Palazzi",
      "S. Piranomonte",
      "A. Rossi",
      "S. Spiro",
      "L. Stella",
      "V. Testa",
      "G. Chincarini",
      "A. Paola",
      "F. Fiore",
      "D. Fugazza",
      "E. Giallongo",
      "E. Maiorano",
      "N. Masetti",
      "F. Pedichini",
      "R. Salvaterra",
      "G. Tagliaferri",
      "S. Vergani"
    ],
    "submission_date": "2009-10-31",
    "semantic_scholar_id": "bc3138d83a2d0bf7b4aa9fee4e0d9e84ae91a637"
  },
  "0812-3349": {
    "title": "The updated spectral catalogue of INTEGRAL gamma-ray bursts",
    "authors": [
      "G. Vianello",
      "D. Götz",
      "S. Mereghetti"
    ],
    "submission_date": "2008-12-17",
    "semantic_scholar_id": "03f8fd7d63d2a3b874f14e154b49f909bbf5c4d5"
  },
  "astro-ph/0701748": {
    "title": "Short-hard gamma-ray bursts",
    "authors": [
      "E. Nakar"
    ],
    "submission_date": "2007-01-25",
    "semantic_scholar_id": "a8f1df266a09dfa346b90bc9bb1e2887b2023451"
  },
  "astro-ph/0612614": {
    "title": "Astrophysics: A burst of new ideas",
    "authors": [
      "Bing Zhang"
    ],
    "submission_date": "2006-12-21",
    "semantic_scholar_id": "f39a11a266c9bba41c0c594e7543f943f99edb5f"
  },
  "astro-ph/0611305": {
    "title": "A Metal-rich Molecular Cloud Surrounds GRB 050904 at Redshift 6.3",
    "authors": [
      "S. Campana",
      "D. Lazzati",
      "Emanuele Ripamonti",
      "R. Perna",
      "S. Covino",
      "G. Tagliaferri",
      "Alessia Moretti",
      "P. Romano",
      "G. Cusumano",
      "G. Chincarini",
      "G. Chincarini"
    ],
    "submission_date": "2006-11-09",
    "semantic_scholar_id": "00c6b8d438ab6d8f9d72513129f417346b0a27f2"
  },
  "astro-ph/0608313": {
    "title": "No supernovae associated with two long-duration γ-ray bursts",
    "authors": [
      "J. Fynbo",
      "D. Watson",
      "C. Thöne",
      "J. Sollerman",
      "J. Bloom",
      "T. Davis",
      "J. Hjorth",
      "P. Jakobsson",
      "U. Jørgensen",
      "J. Graham",
      "A. Fruchter",
      "D. Bersier",
      "L. Kewley",
      "A. Cassan",
      "J. M. C. Ceron",
      "S. Foley",
      "J. Gorosabel",
      "T. Hinse",
      "K. Horne",
      "B. Jensen",
      "S. Klose",
      "D. Kocevski",
      "J. Marquette",
      "D. Perley",
      "E. Ramirez-Ruiz",
      "M. Stritzinger",
      "P. Vreeswijk",
      "R. Wijers",
      "K. Woller",
      "Dong Xu",
      "M. Zub"
    ],
    "submission_date": "2006-08-15",
    "semantic_scholar_id": "f01cd0cbbabd651560ccc762d4ce7b4e76570aa9"
  },
  "astro-ph/0511351": {
    "title": "The Dust-scattered X-Ray Halo around Swift GRB 050724",
    "authors": [
      "S. Vaughan",
      "R. Willingale",
      "P. Romano",
      "J. Osborne",
      "M. Goad",
      "A. Beardmore",
      "D. Burrows",
      "S. Campana",
      "G. Chincarini",
      "S. Covino",
      "A. Moretti",
      "P. O'Brien",
      "K. Page",
      "M. Supper",
      "G. M. U. O. Leicester",
      "I. A. Observatory",
      "P. S. University",
      "Milan-Bicocca University"
    ],
    "submission_date": "2005-11-11",
    "semantic_scholar_id": "3f4827007d68bc045329c09d304a32b6c332720a"
  },
  "astro-ph/0511186": {
    "title": "Dust-scattered X-ray halos around gamma-ray bursts: GRB 031203 revisited and the new case of GRB 050713A",
    "authors": [
      "A. Tiengo",
      "S. Mereghetti"
    ],
    "submission_date": "2005-11-07",
    "semantic_scholar_id": "41c33b8107a103e33bbeb69a62ced88f33a29541"
  },
  "astro-ph/0509477": {
    "title": "The Soft X-Ray Blast in the Apparently Subluminous GRB 031203",
    "authors": [
      "D. Watson",
      "S. Vaughan",
      "R. Willingale",
      "J. Hjorth",
      "S. Foley",
      "J. Fynbo",
      "P. Jakobsson",
      "A. Levan",
      "P. O’Brien",
      "J. Osborne",
      "K. Pedersen",
      "J. Reeves",
      "J. Tedds",
      "M. Watson"
    ],
    "submission_date": "2005-09-15",
    "semantic_scholar_id": "da72c313eb341de2543ec8748a7444b1e85248a7"
  },
  "astro-ph/0508237": {
    "title": "Gas and dust properties in the afterglow spectra of GRB 050730",
    "authors": [
      "R. Starling",
      "P. Vreeswijk",
      "S. Ellison",
      "E. Rol",
      "K. Wiersema",
      "A. Levan",
      "N. Tanvir",
      "R. Wijers",
      "C. Tadhunter",
      "J. Zaurin",
      "R. Delgado",
      "C. Amsterdam",
      "Eső",
      "Victoria",
      "Leicester",
      "Herts",
      "Sheffield",
      "Csic",
      "Nasamsfc"
    ],
    "submission_date": "2005-08-10",
    "semantic_scholar_id": "001bcb3d40166ebaba755f716c58cc140e50b4f8"
  },
  "astro-ph/0312641": {
    "title": "Interstellar Dust Models Consistent with Extinction, Emission, and Abundance Constraints",
    "authors": [
      "V. Zubko",
      "E. Dwek",
      "R. Arendt"
    ],
    "submission_date": "2003-12-29",
    "semantic_scholar_id": "38b9a7753884bfb13456f537766713a1309ce04c"
  },
  "astro-ph/0312603": {
    "title": "The Discovery of an Evolving Dust-scattered X-Ray Halo around GRB 031203",
    "authors": [
      "Simon Vaughan",
      "R. Willingale",
      "P. O’Brien",
      "J. Osborne",
      "J. Reeves",
      "A. Levan",
      "M. Watson",
      "J. Tedds",
      "D. Watson",
      "M. Santos-Lleo",
      "P. Rodríguez-Pascual",
      "N. Schartel"
    ],
    "submission_date": "2003-12-23",
    "semantic_scholar_id": "c31ec04115529cd3368e5fcd333939ceaac267f6"
  },
  "astro-ph/0308346": {
    "title": "INTEGRAL spectrometer SPI’s GRB detection capabilities : GRBs detected inside SPI’s FoV and with the anticoincidence system ACS",
    "authors": [
      "A. Kienlin",
      "V. Beckmann",
      "A. Rau",
      "N. Arend",
      "K. Bennett",
      "B. Mcbreen",
      "P. Connell",
      "S. Deluit",
      "L. Hanlon",
      "K. Hurley",
      "M. Kippen",
      "G. Lichti",
      "L. Moran",
      "P. Preece",
      "J. Roques",
      "V. Schoenfelder",
      "G. Skinner",
      "A. Strong",
      "R. Williams"
    ],
    "submission_date": "2003-08-20",
    "semantic_scholar_id": "67226d3ef9fd62b76cc7a3fd02db9e0466f06a4a"
  },
  "astro-ph/0308251": {
    "title": "Scattering by Interstellar Dust Grains. II. X-Rays",
    "authors": [
      "B. Draine"
    ],
    "submission_date": "2003-08-14",
    "semantic_scholar_id": "876a51ca45ee11cd9092a9ad87dc3ef5710d8a68"
  },
  "astro-ph/0306347": {
    "title": "A very energetic supernova associated with the γ-ray burst of 29 March 2003",
    "authors": [
      "J. Hjorth",
      "J. Sollerman",
      "P. Møller",
      "J. Fynbo",
      "S. Woosley",
      "C. Kouveliotou",
      "N. Tanvir",
      "J. Greiner",
      "M. Andersen",
      "A. Castro-Tirado",
      "J. M. C. Ceron",
      "A. Fruchter",
      "J. Gorosabel",
      "P. Jakobsson",
      "L. Kaper",
      "S. Klose",
      "N. Masetti",
      "H. Pedersen",
      "K. Pedersen",
      "E. Pian",
      "E. Palazzi",
      "J. Rhoads",
      "E. Rol",
      "E. V. Heuvel",
      "P. Vreeswijk",
      "D. Watson",
      "R. Wijers"
    ],
    "submission_date": "2003-06-17",
    "semantic_scholar_id": "b518f3807e62a4537dd7d4542ab163a879c012f8"
  },
  "astro-ph/0304173": {
    "title": "Spectroscopic Discovery of the Supernova 2003dh Associated with GRB 030329",
    "authors": [
      "K. Stanek",
      "T. Matheson",
      "P. Garnavich",
      "P. Martini",
      "P. Berlind",
      "N. Caldwell",
      "P. Challis",
      "Warren R. Brown",
      "R. Schild",
      "K. Krisciunas",
      "M. Calkins",
      "J. Lee",
      "N. Hathi",
      "R. Jansen",
      "R. Windhorst",
      "L. Echevarria",
      "D. Eisenstein",
      "B. Pindor",
      "E. Olszewski",
      "P. Harding",
      "S. Holland",
      "D. Bersier"
    ],
    "submission_date": "2003-04-10",
    "semantic_scholar_id": "fea0fad0c695ed9db515576a4608872d018c5c80"
  },
  "astro-ph/0605199": {
    "title": "The X-Ray Halo of GX 5-1",
    "authors": [
      "Randall K. Smith",
      "T. Dame",
      "E. Costantini",
      "P. Predehl"
    ],
    "submission_date": "2002-12-10",
    "semantic_scholar_id": "b33cdc8809c8bba041fe536ce1c8f0aa213ff707"
  },
  "astro-ph/0206445": {
    "title": "Time-dependent Photoionization in a Dusty Medium. I. Code Description and General Results",
    "authors": [
      "R. Perna",
      "D. Lazzati"
    ],
    "submission_date": "2002-06-26",
    "semantic_scholar_id": "08d0abfdbe44002dc099582f7928cee13acc19e4"
  },
  "astro-ph/0110486": {
    "title": "Determining the location of gamma-ray bursts through the evolution of their soft X-ray absorption",
    "authors": [
      "D. Lazzati",
      "R. Perna"
    ],
    "submission_date": "2001-10-22",
    "semantic_scholar_id": "ce3498ff589c21087b64ce1fc495599a7f5d1006"
  },
  "astro-ph/0011498": {
    "title": "The European Photon Imaging Camera on XMM-Newton: The MOS cameras : The MOS cameras",
    "authors": [
      "M. Turner",
      "A. Abbey",
      "M. Arnaud",
      "M. Balasini",
      "M. Barbera",
      "E. Belsole",
      "P. Bennie",
      "J. Bernard",
      "G. Bignami",
      "Michel Boer",
      "U. Briel",
      "I. Butler",
      "C. Cara",
      "C. Chabaud",
      "R. Cole",
      "A. Collura",
      "M. Conte",
      "A. Cros",
      "M. Denby",
      "P. Dhez",
      "G. Coco",
      "J. Dowson",
      "P. Ferrando",
      "S. Ghizzardi",
      "F. Gianotti",
      "C. Goodall",
      "L. Gretton",
      "R. G. Griffiths",
      "O. Hainaut",
      "J. Hochedez",
      "A. Holland",
      "E. Jourdain",
      "E. Kendziorra",
      "A. Lagostina",
      "R. Lainé",
      "N. Palombara",
      "M. Lortholary",
      "D. Lumb",
      "P. Marty",
      "S. Molendi",
      "C. Pigot",
      "E. Poindron",
      "K. Pounds",
      "J. Reeves",
      "C. Reppin",
      "R. Rothenflug",
      "P. Salvetat",
      "J. Sauvageot",
      "D. Schmitt",
      "S. Sembay",
      "A. Short",
      "J. Spragg",
      "J. Stephen",
      "L. Strüder",
      "A. Tiengo",
      "M. Trifoglio",
      "J. Trümper",
      "S. Vercellone",
      "L. Vigroux",
      "G. Villa",
      "Martin Ward",
      "S. Whitehead",
      "E. Zonca"
    ],
    "submission_date": "2000-11-27",
    "semantic_scholar_id": "f043de28eff6964f8c3cb9fc3e084db2099c5908"
  },
  "astro-ph/9806175": {
    "title": "An unusual supernova in the error box of the γ-ray burst of 25 April 1998",
    "authors": [
      "T. Galama",
      "P. Vreeswijk",
      "J. Paradijs",
      "J. Paradijs",
      "C. Kouveliotou",
      "C. Kouveliotou",
      "T. Augusteijn",
      "H. Böhnhardt",
      "J. Brewer",
      "V. Doublier",
      "J.-F. Gonzalez",
      "B. Leibundgut",
      "C. Lidman",
      "O. Hainaut",
      "F. Patat",
      "J. Heise",
      "J. Zand",
      "K. Hurley",
      "P. Groot",
      "R. Strom",
      "P. Mazzali",
      "K. Iwamoto",
      "K. Nomoto",
      "H. Umeda",
      "Toru Nakamura",
      "T. Young",
      "Tsutomu Suzuki",
      "T. Shigeyama",
      "T. Koshut",
      "M. Kippen",
      "M. Kippen",
      "C. Robinson",
      "C. Robinson",
      "P. Wildt",
      "R. Wijers",
      "N. Tanvir",
      "J. Greiner",
      "E. Pian",
      "E. Palazzi",
      "F. Frontera",
      "N. Masetti",
      "L. Nicastro",
      "M. Feroci",
      "E. Costa",
      "L. Piro",
      "B. Peterson",
      "C. Tinney",
      "B. Boyle",
      "R. Cannon",
      "R. Stathakis",
      "E. Sadler",
      "M. C. Begam",
      "P. Ianna"
    ],
    "submission_date": "1998-06-12",
    "semantic_scholar_id": "8c5567965e5e80582f98fce688b5b05d428ffe58"
  },
  "astro-ph/9712051": {
    "title": "Identifying the Environment and Redshift of Gamma-Ray Burst Afterglows from the Time Dependence of Their Absorption Spectra",
    "authors": [
      "R. Perna",
      "A. Loeb"
    ],
    "submission_date": "1997-12-03",
    "semantic_scholar_id": "08110bf18c6bd3600afa9e5a289cd2fc3d393595"
  },
  "astro-ph/9204001": {
    "title": "Gamma-ray bursts as the death throes of massive binary stars",
    "authors": [
      "R. Narayan",
      "Bohdan Paczy'nski",
      "T. Piran"
    ],
    "submission_date": "1992-04-13",
    "semantic_scholar_id": "8a0bb2115150b36c57ed1fe2f9e1f706b79f84f4"
  }
}