{
  "2307-16606": {
    "title": "Analysis of a Dilute Polymer Model with a Time-Fractional Derivative",
    "authors": [
      "Marvin Fritz",
      "E. Süli",
      "B. Wohlmuth"
    ],
    "submission_date": "2023-07-31",
    "semantic_scholar_id": "e7264e18167f32fc9505cbbd5a4a33f755c035fd"
  },
  "2106-14146": {
    "title": "A second-order accurate numerical scheme for a time-fractional Fokker-Planck equation",
    "authors": [
      "K. Mustapha",
      "O. Knio",
      "O. Maître"
    ],
    "submission_date": "2021-06-27",
    "semantic_scholar_id": "5df9ca8a00db76e1d11b9a320152cfc6eb4268df"
  },
  "2106-10985": {
    "title": "Equivalence between a time-fractional and an integer-order gradient flow: The memory effect reflected in the energy",
    "authors": [
      "Marvin Fritz",
      "U. Khristenko",
      "B. Wohlmuth"
    ],
    "submission_date": "2021-06-21",
    "semantic_scholar_id": "38d172c21c1fe96ca510c6bfe475af694a4c1c0a"
  },
  "2104-03096": {
    "title": "Time-fractional Cahn-Hilliard equation: Well-posedness, degeneracy, and numerical solutions",
    "authors": [
      "Marvin Fritz",
      "M. Rajendran",
      "B. Wohlmuth"
    ],
    "submission_date": "2021-04-07",
    "semantic_scholar_id": "c2e05dbfabad60775ed47280993230fcc68bf805"
  },
  "2103-12834": {
    "title": "A fast and oblivious matrix compression algorithm for Volterra integral operators",
    "authors": [
      "Jürgen Dölz",
      "Herbert Egger",
      "V. Shashkov"
    ],
    "submission_date": "2021-03-23",
    "semantic_scholar_id": "dd1c409d06175d53cd0cc7838c2955680dd31bda"
  },
  "2012-13860": {
    "title": "Uniform stability for a spatially discrete, subdiffusive Fokker–Planck equation",
    "authors": [
      "W. McLean",
      "K. Mustapha"
    ],
    "submission_date": "2020-12-27",
    "semantic_scholar_id": "2e44e3b246e56b0f6557cb8b3cd60f713aa69892"
  },
  "2008-10919": {
    "title": "Bounded weak solutions of time-fractional porous medium type and more general nonlinear and degenerate evolutionary integro-differential equations",
    "authors": [
      "P. Wittbold",
      "P. Wolejko",
      "Rico Zacher"
    ],
    "submission_date": "2020-08-25",
    "semantic_scholar_id": "40e24a089b90bf0edb436a8501b3877f53540b1c"
  },
  "2006-10670": {
    "title": "On a subdiffusive tumour growth model with fractional time derivative",
    "authors": [
      "Marvin Fritz",
      "C. Kuttler",
      "M. Rajendran",
      "L. Scarabosio",
      "B. Wohlmuth"
    ],
    "submission_date": "2020-06-18",
    "semantic_scholar_id": "3d98de321a58d8e0ded3d124fd69832e34d45097"
  },
  "2006-03518": {
    "title": "Approximation of an optimal control problem for the time-fractional Fokker-Planck equation",
    "authors": [
      "F. Camilli",
      "Serikbolsyn Duisembay",
      "Q. Tang"
    ],
    "submission_date": "2020-06-05",
    "semantic_scholar_id": "6cb9fbfc1fd1bfe21d04a390a4b2263c22d67d01"
  },
  "1902-02564": {
    "title": "Existence, uniqueness and regularity of the solution of the time-fractional Fokker–Planck equation with general forcing",
    "authors": [
      "Kim-Ngan Le",
      "W. McLean",
      "M. Stynes"
    ],
    "submission_date": "2019-02-07",
    "semantic_scholar_id": "29dbd437b6af60a259d71d16e5d3e1f20fa12087"
  },
  "1902-00850": {
    "title": "Regularity theory for time-fractional advection-diffusion-reaction equations",
    "authors": [
      "W. McLean",
      "K. Mustapha",
      "Raed Ali",
      "O. Knio"
    ],
    "submission_date": "2019-02-03",
    "semantic_scholar_id": "3c89dd9225665caa68852229d3efad7ee8ba1c21"
  },
  "1902-03204": {
    "title": "A Semidiscrete Finite Element Approximation of a Time-Fractional Fokker-Planck Equation with NonSmooth Initial Data",
    "authors": [
      "Kim-Ngan Le",
      "W. McLean",
      "K. Mustapha"
    ],
    "submission_date": "2018-11-20",
    "semantic_scholar_id": "7017e20a1693e7d208691568b343426e96d12c7f"
  },
  "1810-04836": {
    "title": "Well-posedness of time-fractional advection-diffusion-reaction equations",
    "authors": [
      "W. McLean",
      "K. Mustapha",
      "Raed Ali",
      "O. Knio"
    ],
    "submission_date": "2018-10-11",
    "semantic_scholar_id": "2f051aa326c8804bbcbabbba756215b5fa62e28a"
  },
  "1507-05706": {
    "title": "Numerical Solution of the Time-Fractional Fokker-Planck Equation with General Forcing",
    "authors": [
      "Kim-Ngan Le",
      "W. McLean",
      "K. Mustapha"
    ],
    "submission_date": "2015-07-21",
    "semantic_scholar_id": "53985e13691183160ad3dab82c15442987366377"
  },
  "1310-0209": {
    "title": "Optimal Decay Estimates for Time-Fractional and Other NonLocal Subdiffusion Equations via Energy Methods",
    "authors": [
      "Vicente Vergara",
      "Rico Zacher"
    ],
    "submission_date": "2013-10-01",
    "semantic_scholar_id": "7470fa718f1d9e620edffe3dd0653c82d79a71a3"
  },
  "1105-4592": {
    "title": "A priori estimates for solutions of boundary value problems for fractional-order equations",
    "authors": [
      "A. Alikhanov"
    ],
    "submission_date": "2010-07-07",
    "semantic_scholar_id": "462fb74474b1215038d9a0eda590f6035265ecb5"
  },
  "cond-mat/0703420": {
    "title": "Use and abuse of a fractional Fokker-Planck dynamics for time-dependent driving.",
    "authors": [
      "E. Heinsalu",
      "M. Patriarca",
      "I. Goychuk",
      "P. Hänggi"
    ],
    "submission_date": "2007-03-15",
    "semantic_scholar_id": "352747874b05a9735a809f038253b0e4a81c6118"
  },
  "cond-mat/0301487": {
    "title": "Fractional Fokker-Planck equation for ultraslow kinetics",
    "authors": [
      "A. Chechkin",
      "J. Klafter",
      "Igor M. Sokolov"
    ],
    "submission_date": "2003-01-24",
    "semantic_scholar_id": "332694320297047ae374543661bdbfd3158c14c9"
  },
  "cond-mat/0103468": {
    "title": "Dynamics of annealed systems under external fields: CTRW and the fractional Fokker-Planck equations",
    "authors": [
      "I. Sokolov",
      "A. Blumen",
      "J. Klafter"
    ],
    "submission_date": "2001-03-22",
    "semantic_scholar_id": "97d825934843dd02adc2d6c0ca8f4eaa57561a2a"
  }
}