{
  "2301-09407": {
    "title": "Distinguishing Simple and Complex Contagion Processes on Networks.",
    "authors": [
      "G. Cencetti",
      "Diego Andrés Contreras",
      "Marco Mancastroppa",
      "A. Barrat"
    ],
    "submission_date": "2023-01-23",
    "semantic_scholar_id": "341572dc85976a1a6db1445d18a81dead2cc33de"
  },
  "2206-09490": {
    "title": "A Bounded-Confidence Model of Opinion Dynamics with Heterogeneous Node-Activity Levels",
    "authors": [
      "Grace J. Li",
      "M. A. Porter"
    ],
    "submission_date": "2022-06-19",
    "semantic_scholar_id": "c011785d62b03772b7d58d393ae474db3f06b2b9"
  },
  "2103-06055": {
    "title": "Finite-size effects on the convergence time in continuous-opinion dynamics.",
    "authors": [
      "Hang-Hyun Jo",
      "N. Masuda"
    ],
    "submission_date": "2021-03-10",
    "semantic_scholar_id": "6dea748acedd9a4c1aeb78ee14a26c14226eb194"
  },
  "2102-04298": {
    "title": "The scaling of social interactions across animal species",
    "authors": [
      "Luis E C Rocha",
      "J. Ryckebusch",
      "K. Schoors",
      "Matthew Smith"
    ],
    "submission_date": "2021-02-08",
    "semantic_scholar_id": "76885e7f092dcc0c52bcdd7bf279d9d3405f1886"
  },
  "1811-11888": {
    "title": "Reality-inspired voter models: A mini-review",
    "authors": [
      "S. Redner"
    ],
    "submission_date": "2018-11-29",
    "semantic_scholar_id": "390d5fe0298dfd79fd643957378ee03076c514bd"
  },
  "1811-03341": {
    "title": "Modelling opinion dynamics in the age of algorithmic personalisation",
    "authors": [
      "N. Perra",
      "L. E. C. Rocha"
    ],
    "submission_date": "2018-11-08",
    "semantic_scholar_id": "f563a49b548d99ebcd68c428989718c036925ec2"
  },
  "1710-07606": {
    "title": "Complex Contagions: A Decade in Review",
    "authors": [
      "Douglas Guilbeault",
      "J. Becker",
      "Damon Centola"
    ],
    "submission_date": "2017-10-20",
    "semantic_scholar_id": "32d9e7bbfce8639bda32efb443a16e1514b8053e"
  },
  "1704-07767": {
    "title": "The emergence of consensus: a primer",
    "authors": [
      "Andrea Baronchelli"
    ],
    "submission_date": "2017-04-25",
    "semantic_scholar_id": "4aac25dc720beca1a5ff724140a5b832454aa2db"
  },
  "1612-05483": {
    "title": "The Role of Homophily in the Emergence of Opinion Controversies",
    "authors": [
      "F. Gargiulo",
      "Yérali Gandica"
    ],
    "submission_date": "2016-12-16",
    "semantic_scholar_id": "b5e482a344f5adf9de5932e5cd6f376fc0433f3f"
  },
  "1608-00607": {
    "title": "Configuring Random Graph Models with Fixed Degree Sequences",
    "authors": [
      "B. Fosdick",
      "D. Larremore",
      "Joel Nishimura",
      "J. Ugander"
    ],
    "submission_date": "2016-08-01",
    "semantic_scholar_id": "517ff59294dba86e4d6264f659347355e3caa822"
  },
  "1607-01032": {
    "title": "Echo Chambers: Emotional Contagion and Group Polarization on Facebook",
    "authors": [
      "Michela Del Vicario",
      "G. Vivaldo",
      "Alessandro Bessi",
      "Fabiana Zollo",
      "Antonio Scala",
      "G. Caldarelli",
      "Walter Quattrociocchi"
    ],
    "submission_date": "2016-06-29",
    "semantic_scholar_id": "72d5fe02b24f757e4d7669f47fc17774e7120439"
  },
  "1601-01490": {
    "title": "A Gillespie Algorithm for Non-Markovian Stochastic Processes",
    "authors": [
      "N. Masuda",
      "Luis E C Rocha"
    ],
    "submission_date": "2016-01-07",
    "semantic_scholar_id": "0e700d89714d2c267e5ada8404d82334da30ca28"
  },
  "1403-3344": {
    "title": "Collective attention in the age of (mis)information",
    "authors": [
      "Delia Mocanu",
      "L. Rossi",
      "Qian Zhang",
      "M. Karsai",
      "Walter Quattrociocchi"
    ],
    "submission_date": "2014-03-13",
    "semantic_scholar_id": "f22bf8053d658029a1487d6ff823777917680092"
  },
  "1309-4155": {
    "title": "Diffusion on networked systems is a question of time or structure",
    "authors": [
      "Jean-Charles Delvenne",
      "R. Lambiotte",
      "Luis E C Rocha"
    ],
    "submission_date": "2013-09-17",
    "semantic_scholar_id": "50f95a1b4412c1bce7a2ee305a86b414cb844b97"
  },
  "1108-4841": {
    "title": "Simulation of an SEIR infectious disease model on the dynamic contact network of conference attendees",
    "authors": [
      "J. Stehlé",
      "N. Voirin",
      "A. Barrat",
      "C. Cattuto",
      "V. Colizza",
      "L. Isella",
      "C. Régis",
      "J. Pinton",
      "N. Khanafer",
      "W. van den Broeck",
      "P. Vanhems"
    ],
    "submission_date": "2011-07-19",
    "semantic_scholar_id": "fb3587b7abca589772b4646544e87e38a4c4fa78"
  },
  "1006-2856": {
    "title": "Simulated Epidemics in an Empirical Spatiotemporal Network of 50,185 Sexual Contacts",
    "authors": [
      "Luis E C Rocha",
      "F. Liljeros",
      "Petter Holme"
    ],
    "submission_date": "2010-06-14",
    "semantic_scholar_id": "4f1c7b1b9c8f5510baa5d9be00044d51bdba75cf"
  },
  "1006-2125": {
    "title": "Small But Slow World: How Network Topology and Burstiness Slow Down Spreading",
    "authors": [
      "M. Karsai",
      "Mikko Kivelä",
      "R. K. Pan",
      "K. Kaski",
      "J. Kertész",
      "A. Barabási",
      "J. Saramäki"
    ],
    "submission_date": "2010-06-10",
    "semantic_scholar_id": "49cca23a426d3e504bd48589ea2a3cebb83df5ff"
  },
  "0710-3256": {
    "title": "Statistical physics of social dynamics",
    "authors": [
      "C. Castellano",
      "S. Fortunato",
      "V. Loreto"
    ],
    "submission_date": "2007-10-17",
    "semantic_scholar_id": "e419cfbbdd1de7f9a2ed6bb2d5392840dcb2a4fd"
  },
  "physics/0610233": {
    "title": "Burstiness and memory in complex systems",
    "authors": [
      "K. Goh",
      "A. Barabási"
    ],
    "submission_date": "2006-10-25",
    "semantic_scholar_id": "17afd11e5320840e4ce74a688c21ac8dc1987350"
  },
  "physics/0602124": {
    "title": "Modularity and community structure in networks.",
    "authors": [
      "M. Newman"
    ],
    "submission_date": "2006-02-17",
    "semantic_scholar_id": "2a91c8ff11a828209f10714cfc46fd929a51e9dc"
  },
  "physics/0510216": {
    "title": "Comment on Barabasi, Nature 435, 207 (2005)",
    "authors": [
      "Daniel B. Stouffer",
      "R. Malmgren",
      "L. A. N. Amaral"
    ],
    "submission_date": "2005-10-25",
    "semantic_scholar_id": "5029720bdeab0d4053eb621a2771a378909e3789"
  },
  "cond-mat/0410669": {
    "title": "Heterogeneous beliefs, segregation, and extremism in the making of public opinions.",
    "authors": [
      "S. Galam"
    ],
    "submission_date": "2004-10-26",
    "semantic_scholar_id": "4d7be15693cb06d58318c995d7b53dded8a76e53"
  },
  "cond-mat/0406054": {
    "title": "UNIVERSALITY OF THE THRESHOLD FOR COMPLETE CONSENSUS FOR THE OPINION DYNAMICS OF DEFFUANT et al",
    "authors": [
      "S. Fortunato"
    ],
    "submission_date": "2004-06-02",
    "semantic_scholar_id": "1725f7c72265064a3d59b9c962d7e6818d6d4a09"
  },
  "cond-mat/0101130": {
    "title": "Opinion evolution in closed community",
    "authors": [
      "K. Sznajd-Weron",
      "J. Sznajd"
    ],
    "submission_date": "2000-09-01",
    "semantic_scholar_id": "4302d4badd3a3b21d822fbeed1339e64fd9a01dd"
  }
}